Metadata-Version: 1.1
Name: pypugly
Version: 0.2.0
Summary: Another HTML generator based on JADE.
Home-page: https://github.com/zerotk/pypugly
Author: Alexandre Andrade
Author-email: kaniabi@gmail.com
License: UNKNOWN
Keywords: generator,html,jade
Platform: UNKNOWN
Classifier: Development Status :: 3 - Alpha
Classifier: Intended Audience :: Developers
Classifier: Topic :: Software Development :: Libraries :: Python Modules
Classifier: License :: OSI Approved :: MIT License
Classifier: Programming Language :: Python :: 2
Classifier: Programming Language :: Python :: 2.7
Classifier: Programming Language :: Python :: 3
Classifier: Programming Language :: Python :: 3.5
